lightdsa/__init__.py
lightdsa/algorithms/__init__.py
lightdsa/algorithms/dsa.py
lightdsa/algorithms/ecdsa.py
lightdsa/algorithms/eddsa.py
lightdsa/algorithms/rsa.py
lightdsa/commons/__init__.py
lightdsa/commons/logger.py
lightdsa/commons/transformation.py
lightdsa/interfaces/__init__.py
lightdsa/interfaces/signatures.py
lightdsa-0.0.2.data/data/README.md
lightdsa-0.0.2.data/data/requirements.txt
lightdsa-0.0.2.dist-info/LICENSE
lightdsa-0.0.2.dist-info/METADATA
lightdsa-0.0.2.dist-info/WHEEL
lightdsa-0.0.2.dist-info/top_level.txt
lightdsa-0.0.2.dist-info/RECORD
