Metadata-Version: 2.1
Name: lightdsa
Version: 0.0.2
Summary: A Lightweight Digital Signature Algorithm Library for Python
Home-page: https://github.com/serengil/LightDSA
Author: Sefik Ilkin Serengil
Author-email: serengil@gmail.com
License: UNKNOWN
Platform: UNKNOWN
Classifier: Programming Language :: Python :: 3
Classifier: License :: OSI Approved :: MIT License
Classifier: Operating System :: OS Independent
Requires-Python: >=3.5.5
License-File: LICENSE
Requires-Dist: lightecc
Requires-Dist: sympy
Requires-Dist: tqdm
